roadmapper/__init__.py
roadmapper/alignment.py
roadmapper/colourtheme.py
roadmapper/footer.py
roadmapper/group.py
roadmapper/helper.py
roadmapper/logo.py
roadmapper/marker.py
roadmapper/milestone.py
roadmapper/painter.py
roadmapper/roadmap.py
roadmapper/subtitle.py
roadmapper/task.py
roadmapper/timeline.py
roadmapper/timelineitem.py
roadmapper/timelineitemyear.py
roadmapper/timelinelocale.py
roadmapper/timelinemode.py
roadmapper/title.py
roadmapper/version.py
roadmapper-1.5.5.dist-info/licenses/LICENSE.md
tests/__init__.py
tests/compare_generated_roadmaps_test.py
tests/conftest.py
tests/roadmap_draw_test.py
tests/test_alignment.py
tests/test_cases.py
tests/test_cases_svg.py
tests/test_defects.py
tests/test_milestone.py
tests/test_painter.py
tests/test_roadmapper.py
tests/test_roadmapper_svg.py
tests/roadmap_generators/__init__.py
tests/roadmap_generators/colour_theme.py
tests/roadmap_generators/colour_theme_extensive.py
tests/roadmap_generators/milestone_text_alignment.py
tests/roadmap_generators/roadmap_abc.py
tests/roadmap_generators/roadmap_generator.py
roadmapper-1.5.5.dist-info/METADATA
roadmapper-1.5.5.dist-info/WHEEL
roadmapper-1.5.5.dist-info/top_level.txt
roadmapper-1.5.5.dist-info/RECORD
