Metadata-Version: 2.4
Name: roadmapper
Version: 1.5.5
Summary: Roadmapper. A Roadmap-as-Code (RaC) python library for generating a roadmap by using python code
Author: CS Goh
License-Expression: MIT
Project-URL: Homepage, https://github.com/csgoh/roadmapper
Project-URL: Bug Tracker, https://github.com/csgoh/roadmapper/issues
Classifier: Programming Language :: Python :: 3.10
Classifier: Operating System :: OS Independent
Requires-Python: >=3.10
License-File: LICENSE.md
Requires-Dist: Pillow>=10.0.0
Requires-Dist: python-dateutil>=2.8.2
Requires-Dist: drawsvg>=2.2.0
Dynamic: license-file
